{
    "inputMessageMetadata": {
        "messagePayload": {
            "connectorName": "#_custom_mule_metadata_type_#",
            "typeId": "NotasCSV"
        }
    },
    "outputMessageMetadata": {
        "messagePayload": {
            "model": {
                "connectorName": "#_custom_mule_metadata_type_#",
                "typeId": "NotasJSON"
            },
            "isArray": false,
            "dataType": "LIST",
            "metaDataModelPropertiesManager": {
                "properties": []
            }
        }
    },
    "id": "11fb123c-9c91-47f7-ae5d-1a5dd080432b",
    "version": "5.2.0.0"
}